PyPonding/FE.py
PyPonding/PondingLoadCell.py
PyPonding/PondingLoadCell_OPS.py
PyPonding/__init__.py
PyPonding/Marino/Marino.py
PyPonding/Marino/__init__.py
PyPonding/structures/__init__.py
PyPonding/structures/basic_structure.py
PyPonding/structures/bay.py
PyPonding/structures/elastic_beam.py
PyPonding/structures/idealized_bay.py
PyPonding/structures/idealized_joist_bay.py
PyPonding/structures/joist.py
PyPonding/structures/osu_test.py
PyPonding/structures/roof2x3.py
PyPonding/structures/roof2x3_Xdir.py
PyPonding/structures/roof2x3_Ydir.py
PyPonding/structures/steel_beam.py
PyPonding/structures/wide_flange.py
PyPonding-1.0.0.dist-info/LICENSE
PyPonding-1.0.0.dist-info/METADATA
PyPonding-1.0.0.dist-info/WHEEL
PyPonding-1.0.0.dist-info/top_level.txt
PyPonding-1.0.0.dist-info/RECORD
