Metadata-Version: 2.1
Name: PyPonding
Version: 1.0.0
Summary: A Python library for modeling ponding on framed structures.
Home-page: https://github.com/denavit/PyPonding
Author: Mark Denavit
Author-email: mdenavit@utk.edu
License: MIT
Requires-Python: >=3.7
License-File: LICENSE
